ensemble_transformers/__init__.py
ensemble_transformers/__version__.py
ensemble_transformers/base.py
ensemble_transformers/config.py
ensemble_transformers/ensemble.py
ensemble_transformers/output.py
ensemble_transformers-0.0.2.dist-info/LICENSE
ensemble_transformers-0.0.2.dist-info/METADATA
ensemble_transformers-0.0.2.dist-info/WHEEL
ensemble_transformers-0.0.2.dist-info/top_level.txt
ensemble_transformers-0.0.2.dist-info/RECORD
