Metadata-Version: 2.1
Name: ensemble-transformers
Version: 0.0.2
Summary: Ensembling Hugging Face Transformers made easy
Home-page: https://github.com/jaketae/ensemble-transformers
Author: Jake Tae
Author-email: jaesungtae@gmail.com
License: UNKNOWN
Platform: UNKNOWN
Classifier: Programming Language :: Python :: 3.7
Classifier: Programming Language :: Python :: 3.8
Classifier: Programming Language :: Python :: 3.9
Classifier: Intended Audience :: Developers
Classifier: Intended Audience :: Science/Research
Classifier: Topic :: Scientific/Engineering :: Artificial Intelligence
Requires-Python: >=3.7
Requires-Dist: torch
Requires-Dist: transformers
